LICENSE
MANIFEST.in
README.rst
setup.py
django_saveall.egg-info/PKG-INFO
django_saveall.egg-info/SOURCES.txt
django_saveall.egg-info/dependency_links.txt
django_saveall.egg-info/top_level.txt
saveall/__init__.py
saveall/admin.py
saveall/models.py
saveall/views.py
saveall/management/__init__.py
saveall/management/__init__.pyc
saveall/management/commands/__init__.py
saveall/management/commands/__init__.pyc
saveall/management/commands/saveall.py
saveall/tests/__init__.py
saveall/tests/__init__.pyc
saveall/tests/models.py
saveall/tests/models.pyc
saveall/tests/test_command.py
saveall/tests/test_command.pyc
saveall/tests/test_models.py
saveall/tests/test_models.pyc