Metadata-Version: 1.1
Name: django-saveall
Version: 0.1.5
Summary: A simple Django app that adds a custom django-admin command for saving model instances throughout a project.
Home-page: https://github.com/gabriel-card/saveall
Author: Gabriel Cardoso
Author-email: gabriel.cardoso@corp.globo.com
License: MIT License
Platform: UNKNOWN
Classifier: Environment :: Web Environment
Classifier: Framework :: Django :: 1.7
Classifier: Intended Audience :: Developers
Classifier: License :: OSI Approved :: MIT License
Classifier: Operating System :: OS Independent
Classifier: Programming Language :: Python
Classifier: Programming Language :: Python :: 2.7
Classifier: Topic :: Database
Classifier: Topic :: Internet :: WWW/HTTP :: Dynamic Content
